django_redis_sdk/__init__.py
django_redis_sdk/connection.py
django_redis_sdk/cache_backend/__init__.py
django_redis_sdk/cache_backend/base.py
django_redis_sdk/cache_backend/dummy.py
django_redis_sdk/cache_backend/multiple.py
django_redis_sdk/cache_backend/single.py
django_redis_sdk/clients/__init__.py
django_redis_sdk/clients/base_client.py
django_redis_sdk/clients/shard_client.py
django_redis_sdk/compressors/__init__.py
django_redis_sdk/compressors/base_compressor.py
django_redis_sdk/compressors/zlib_compressor.py
django_redis_sdk/serializers/__init__.py
django_redis_sdk/serializers/base_serializer.py
django_redis_sdk/serializers/json_serializer.py
django_redis_sdk/serializers/pickle_serializer.py
django_redis_sdk/utils/__init__.py
django_redis_sdk/utils/common_utils.py
django_redis_sdk/utils/exceptions.py
django_redis_sdk/utils/hashring.py
django_redis_sdk-1.0.0.0.dist-info/LICENSE
django_redis_sdk-1.0.0.0.dist-info/METADATA
django_redis_sdk-1.0.0.0.dist-info/WHEEL
django_redis_sdk-1.0.0.0.dist-info/top_level.txt
django_redis_sdk-1.0.0.0.dist-info/RECORD
