Metadata-Version: 2.1
Name: django-redis-sdk
Version: 1.0.0.0
Summary: Django Redis sdk
Home-page: https://github.com/midhuncnair/django_redis_sdk
Author: Midhun C Nair
Author-email: midhunch@gmail.com
License: MIT LICENSE
Keywords: django,redis,django-redis-sdk,redis-cache,cache,django-cache,django-redis-cache
Platform: UNKNOWN
Classifier: Programming Language :: Python :: 3
Classifier: License :: OSI Approved :: MIT License
Classifier: Operating System :: OS Independent
Requires-Python: >=3.5.9
Requires-Dist: docutils (>=0.3)
Requires-Dist: redis (>=3.0.1)
Requires-Dist: django (>=2.2)
